<?xml version="1.0" encoding="UTF-8"?><items hlblockUid="RealEstateAgents" exchangeVersion="2"><item><field name="UF_ACTIVITY"><value>1</value></field><field name="UF_NAME"><value>Шварценберг Владислав Львович</value></field><field name="UF_EMAIL"><value>shvartsenberg2015@mail.ru</value></field><field name="UF_PHONE"><value>+79104355607</value></field><field name="UF_TYPE_OF_ACTIVITY"><value>2</value></field><field name="UF_PHOTO"><value name="ZoXCKDy2e1Q.jpg">uf/c12/gglenn53hxhk563xj9s6svp6qau4y0ly.jpg</value></field></item></items>